{"geometry":{"type":"Point","coordinates":[-87.910036,30.617845]},"type":"Feature","bbox":[-87.910036,30.617845,-87.910036,30.617845],"properties":{"geom:longitude":-87.910036,"sg:website":"http://www.osgrm.com","sg:classifiers":[{"category":"Professional","type":"Services","subcategory":"Computer Services"}],"sg:address":"Entrances 4&5 8th March Street, 14","wof:hierarchy":[{"venue_id":"102147783","neighbourhood_id":85827259,"country_id":85633793,"locality_id":85914695,"county_id":102085469,"region_id":85688675}],"iso:country":"RU","wof:geomhash":"ddc7ba7f007fe002c834a383803acda1","wof:name":"OSG Records Management","src:geom":"simplegeo","wof:supersedes":[],"wof:id":"102147783","wof:breaches":[],"geom:area":0.000000,"sg:owner":"simplegeo","sg:postcode":"125083","geom:latitude":30.617845,"sg:href":"http://api.simplegeo.com/1.0/features/SG_3TCwbLZTDvxKgiSM193kJT_30.617845_-87.910036@1308163242.json","sg:city":"Moscow","wof:belongsto":[85827259,85633793,85914695,102085469,85688675],"wof:placetype":"venue","wof:lastmodified":1440555955,"wof:superseded_by":[],"wof:concordances":{"sg:id":"SG_3TCwbLZTDvxKgiSM193kJT_30.617845_-87.910036@1308163242"},"wof:parent_id":85827259}}