{
  "type": "Feature",
  "properties": {
    "iso:country":"RU",
    "sg:address":"Entrances 4&5 8th March Street, 14",
    "sg:city":"Moscow",
    "sg:classifiers":[
        {
            "category":"Professional",
            "subcategory":"Computer Services",
            "type":"Services"
        }
    ],
    "sg:href":"http://api.simplegeo.com/1.0/features/SG_3TCwbLZTDvxKgiSM193kJT_30.617845_-87.910036@1308163242.json",
    "sg:postcode":"125083",
    "sg:website":"http://www.osgrm.com",
    "wof:name":"OSG Records Management",
    "wof:placetype":"venue"
},
  "geometry": {"coordinates":[-87.91003600000001,30.617845],"type":"Point"}
}