{
  "type": "Feature",
  "properties": {
    "iso:country":"RU",
    "sg:address":"Malaya Morskaya st. 11, office 218",
    "sg:city":"St Petersburg",
    "sg:classifiers":[
        {
            "category":"Professional",
            "subcategory":"Computer Services",
            "type":"Services"
        }
    ],
    "sg:href":"http://api.simplegeo.com/1.0/features/SG_69IZkoB9j9Meh7ATFPFbAP_59.935281_30.311872@1308163236.json",
    "sg:postcode":"191178",
    "sg:tags":[
        "messaging",
        "loudtalks",
        "voice",
        "p2p"
    ],
    "sg:website":"http://loudtalks.com/",
    "wof:name":"Loudtalks",
    "wof:placetype":"venue"
},
  "geometry": {"coordinates":[30.311872,59.935281],"type":"Point"}
}