{"geometry":{"type":"Point","coordinates":[30.311872,59.935281]},"type":"Feature","bbox":[30.311872,59.935281,30.311872,59.935281],"properties":{"sg:tags":["messaging","loudtalks","voice","p2p"],"geom:longitude":30.311872,"sg:website":"http://loudtalks.com/","sg:classifiers":[{"category":"Professional","type":"Services","subcategory":"Computer Services"}],"sg:address":"Malaya Morskaya st. 11, office 218","wof:hierarchy":[{"locality_id":102008121,"venue_id":"102147775","country_id":85632685,"region_id":85688069,"neighbourhood_id":85903361}],"iso:country":"RU","wof:geomhash":"d7f0c4a3d44239dab55d79266574b301","wof:name":"Loudtalks","src:geom":"simplegeo","wof:supersedes":[],"wof:id":"102147775","wof:breaches":[],"geom:area":0.000000,"sg:owner":"simplegeo","sg:postcode":"191178","geom:latitude":59.935281,"sg:href":"http://api.simplegeo.com/1.0/features/SG_69IZkoB9j9Meh7ATFPFbAP_59.935281_30.311872@1308163236.json","sg:city":"St Petersburg","wof:lastmodified":1440555955,"wof:belongsto":[102008121,85632685,85688069,85903361],"wof:placetype":"venue","wof:superseded_by":[],"wof:concordances":{"sg:id":"SG_69IZkoB9j9Meh7ATFPFbAP_59.935281_30.311872@1308163236"},"wof:parent_id":85903361}}